mpadam/__init__.py
mpadam/adam.py
mpadam/api.py
mpadam/config.py
mpadam/grad_scaler.py
mpadam/triton_kernels.py
mpadam-1.0.7.dist-info/licenses/LICENSE
mpadam-1.0.7.dist-info/METADATA
mpadam-1.0.7.dist-info/WHEEL
mpadam-1.0.7.dist-info/top_level.txt
mpadam-1.0.7.dist-info/RECORD
