Metadata-Version: 2.4
Name: mpadam
Version: 1.0.7
Summary: Mixed Precision Adam optimizer
Author-email: Alexander Lyulkov <alex.lyulkov@hotmail.com>
License-Expression: Apache-2.0
Project-URL: Homepage, https://github.com/alexlyulkov/MPAdam
Classifier: Programming Language :: Python :: 3
Classifier: Operating System :: OS Independent
Requires-Python: >=3.9
License-File: LICENSE
Requires-Dist: torch
Requires-Dist: triton
Dynamic: license-file
